pyams_form/__init__.py
pyams_form/action.py
pyams_form/ajax.py
pyams_form/button.py
pyams_form/contentprovider.py
pyams_form/converter.py
pyams_form/datamanager.py
pyams_form/error.py
pyams_form/events.py
pyams_form/field.py
pyams_form/form.py
pyams_form/group.py
pyams_form/hint.py
pyams_form/include.py
pyams_form/object.py
pyams_form/outputchecker.py
pyams_form/subform.py
pyams_form/template.py
pyams_form/term.py
pyams_form/testing.py
pyams_form/util.py
pyams_form/validator.py
pyams_form/value.py
pyams_form/widget.py
pyams_form/browser/__init__.py
pyams_form/browser/button.py
pyams_form/browser/checkbox.py
pyams_form/browser/file.py
pyams_form/browser/image.py
pyams_form/browser/interfaces.py
pyams_form/browser/multi.py
pyams_form/browser/object.py
pyams_form/browser/orderedselect.py
pyams_form/browser/password.py
pyams_form/browser/radio.py
pyams_form/browser/select.py
pyams_form/browser/submit.py
pyams_form/browser/text.py
pyams_form/browser/textarea.py
pyams_form/browser/textlines.py
pyams_form/browser/widget.py
pyams_form/browser/resources/js/orderedselect-input.js
pyams_form/browser/resources/js/orderedselect-input.min.js
pyams_form/doctests/README.rst
pyams_form/doctests/action.rst
pyams_form/doctests/ajax.rst
pyams_form/doctests/browser.rst
pyams_form/doctests/button.rst
pyams_form/doctests/contentprovider.rst
pyams_form/doctests/converter.rst
pyams_form/doctests/datamanager.rst
pyams_form/doctests/error.rst
pyams_form/doctests/field.rst
pyams_form/doctests/form.rst
pyams_form/doctests/group.rst
pyams_form/doctests/hint.rst
pyams_form/doctests/index-browser.rst
pyams_form/doctests/index.rst
pyams_form/doctests/object-caveat.rst
pyams_form/doctests/security.rst
pyams_form/doctests/subform.rst
pyams_form/doctests/term.rst
pyams_form/doctests/testing.rst
pyams_form/doctests/util.rst
pyams_form/doctests/validator.rst
pyams_form/doctests/value.rst
pyams_form/doctests/widget-button.rst
pyams_form/doctests/widget-checkbox.rst
pyams_form-2.1.3.dist-info/LICENSE
pyams_form-2.1.3.dist-info/METADATA
pyams_form-2.1.3.dist-info/WHEEL
pyams_form-2.1.3.dist-info/entry_points.txt
pyams_form-2.1.3.dist-info/namespace_packages.txt
pyams_form-2.1.3.dist-info/top_level.txt
pyams_form-2.1.3.dist-info/RECORD
