Metadata-Version: 2.1
Name: pyams_form
Version: 2.1.3
Summary: PyAMS forms management package
Home-page: https://pyams.readthedocs.io
Author: Thierry Florac
Author-email: tflorac@ulthar.net
License: ZPL
Keywords: Pyramid PyAMS
Classifier: License :: OSI Approved :: Zope Public License
Classifier: Development Status :: 4 - Beta
Classifier: Programming Language :: Python
Classifier: Framework :: Pyramid
Classifier: Topic :: Software Development :: Libraries :: Python Modules
Requires-Python: >=3.7
License-File: LICENSE
Requires-Dist: setuptools
Requires-Dist: fanstatic
Requires-Dist: lxml
Requires-Dist: persistent
Requires-Dist: pyams-layer
Requires-Dist: pyams-pagelet
Requires-Dist: pyams-security
Requires-Dist: pyams-template
Requires-Dist: pyams-utils
Requires-Dist: pyramid>=2.0.0
Requires-Dist: pyramid-chameleon
Requires-Dist: six
Requires-Dist: venusian
Requires-Dist: zope.component
Requires-Dist: zope.contentprovider
Requires-Dist: zope.contenttype
Requires-Dist: zope.i18n
Requires-Dist: zope.interface
Requires-Dist: zope.lifecycleevent
Requires-Dist: zope.location
Requires-Dist: zope.schema
Requires-Dist: zope.security
Requires-Dist: zope.testing
Provides-Extra: test
Requires-Dist: pyams-i18n; extra == "test"
Requires-Dist: zc.sourcefactory; extra == "test"
Requires-Dist: zope.testing; extra == "test"
